aisql/__init__.py
aisql/cli.py
aisql/lib.py
aisql/main.py
aisql/models.py
aisql/server.py
aisql/schemas/__init__.py
aisql/schemas/mongodb.py
aisql/schemas/postgresql.py
aisql/templates/demo.html
aisql-0.1.0.dist-info/METADATA
aisql-0.1.0.dist-info/WHEEL
aisql-0.1.0.dist-info/entry_points.txt
aisql-0.1.0.dist-info/licenses/LICENSE
aisql-0.1.0.dist-info/RECORD
