Metadata-Version: 2.4
Name: aisql
Version: 0.1.0
Summary: AI-powered SQL and MongoDB query generator that converts natural language to optimized database queries
License: MIT
License-File: LICENSE
Keywords: ai,langchain,mongodb,natural-language,query-generator,sql
Classifier: Development Status :: 3 - Alpha
Classifier: Intended Audience :: Developers
Classifier: License :: OSI Approved :: MIT License
Classifier: Programming Language :: Python :: 3
Classifier: Programming Language :: Python :: 3.10
Classifier: Programming Language :: Python :: 3.11
Classifier: Programming Language :: Python :: 3.12
Requires-Python: >=3.10
Requires-Dist: chromadb>=0.6.3
Requires-Dist: fastapi>=0.115.11
Requires-Dist: jinja2>=3.1.6
Requires-Dist: langchain-chroma>=0.2.2
Requires-Dist: langchain-community>=0.3.20
Requires-Dist: langchain-openai>=0.3.9
Requires-Dist: langchain>=0.3.21
Requires-Dist: openai>=1.68.2
Requires-Dist: uvicorn>=0.34.0
Provides-Extra: dev
Requires-Dist: black>=25.1.0; extra == 'dev'
Requires-Dist: pylint>=3.3.6; extra == 'dev'
Requires-Dist: pytest>=8.3.5; extra == 'dev'
